website_sitemap_parser/__init__.py
website_sitemap_parser/config.py
website_sitemap_parser/elements.py
website_sitemap_parser/parsers/__init__.py
website_sitemap_parser/parsers/robots_parser.py
website_sitemap_parser/parsers/xml_parser.py
website_sitemap_parser-0.0.14.dist-info/METADATA
website_sitemap_parser-0.0.14.dist-info/WHEEL
website_sitemap_parser-0.0.14.dist-info/top_level.txt
website_sitemap_parser-0.0.14.dist-info/RECORD
