Metadata-Version: 2.1
Name: website-sitemap-parser
Version: 0.0.14
Summary: Website Sitemap Parser
Home-page: https://github.com/bartmachielsen/website-sitemap-parser
Author: Bart Machielsen
Author-email: bartmachielsen@gmail.com
License: UNKNOWN
Platform: UNKNOWN
Classifier: Programming Language :: Python :: 3
Classifier: License :: OSI Approved :: MIT License
Classifier: Operating System :: OS Independent
Requires-Dist: requests
Requires-Dist: stopit
Requires-Dist: dateparser
